{"v":"5.7.8","fr":60,"ip":0,"op":115,"w":500,"h":500,"nm":"15-family","ddd":0,"assets":[],"layers":[{"ddd":0,"ind":1,"ty":3,"nm":"Main Stroke width - Color Ctrl","parent":8,"sr":1,"ks":{"o":{"a":0,"k":0,"ix":11},"r":{"a":0,"k":0,"ix":10},"p":{"a":0,"k":[0,0,0],"ix":2,"l":2},"a":{"a":0,"k":[50,50,0],"ix":1,"l":2},"s":{"a":0,"k":[100,100,100],"ix":6,"l":2}},"ao":0,"ef":[{"ty":5,"nm":"Stroke width","np":3,"mn":"ADBE Slider Control","ix":1,"en":1,"ef":[{"ty":0,"nm":"Deslizador","mn":"ADBE Slider Control-0001","ix":1,"v":{"a":0,"k":16,"ix":1}}]},{"ty":5,"nm":"Base Color","np":3,"mn":"ADBE Color Control","ix":2,"en":1,"ef":[{"ty":2,"nm":"Color","mn":"ADBE Color Control-0001","ix":1,"v":{"a":0,"k":[0,0,0,1],"ix":1}}]},{"ty":5,"nm":"Highlight","np":3,"mn":"ADBE Color Control","ix":3,"en":1,"ef":[{"ty":2,"nm":"Color","mn":"ADBE Color Control-0001","ix":1,"v":{"a":0,"k":[0.20000000298,0.800000011921,0.800000011921,1],"ix":1}}]}],"ip":0,"op":115,"st":0,"bm":0},{"ddd":0,"ind":2,"ty":4,"nm":"Child","sr":1,"ks":{"o":{"a":0,"k":100,"ix":11},"r":{"a":0,"k":0,"ix":10},"p":{"a":0,"k":[260.678,360.506,0],"ix":2,"l":2},"a":{"a":0,"k":[97.348,105.495,0],"ix":1,"l":2},"s":{"a":0,"k":[100,100,100],"ix":6,"l":2}},"ao":0,"shapes":[{"ty":"gr","it":[{"ind":0,"ty":"sh","ix":1,"ks":{"a":1,"k":[{"i":{"x":0.833,"y":0.833},"o":{"x":0.333,"y":0},"t":5,"s":[{"i":[[14.498,0],[0,0],[0,-14.498],[0,0],[-17.702,0],[0,17.702],[0,0]],"o":[[0,0],[-14.498,0],[0,0],[0,17.702],[17.702,0],[0,0],[0,-14.498]],"v":[[5.802,-66.995],[-5.802,-66.995],[-32.053,-40.744],[-32.053,-16.711],[0,15.341],[32.053,-16.711],[32.053,-40.744]],"c":true}]},{"i":{"x":0.833,"y":0.833},"o":{"x":0.167,"y":0.167},"t":20,"s":[{"i":[[14.317,1.862],[0,0],[1.862,-14.317],[0,0],[-17.481,-2.274],[-2.274,17.481],[0,0]],"o":[[0,0],[-14.317,-1.862],[0,0],[-2.274,17.481],[17.481,2.274],[0,0],[1.862,-14.317]],"v":[[16.189,-65.144],[4.73,-66.635],[-24.565,-44.084],[-27.652,-20.352],[-0.117,15.418],[35.653,-12.116],[38.74,-35.849]],"c":true}]},{"i":{"x":0.833,"y":0.833},"o":{"x":0.167,"y":0.167},"t":45,"s":[{"i":[[14.226,2.794],[0,0],[2.794,-14.226],[0,0],[-17.37,-3.411],[-3.411,17.37],[0,0]],"o":[[0,0],[-14.226,-2.794],[0,0],[-3.411,17.37],[17.37,3.411],[0,0],[2.794,-14.226]],"v":[[21.383,-64.219],[9.996,-66.455],[-20.821,-45.754],[-25.452,-22.172],[-0.176,15.456],[37.453,-9.819],[42.084,-33.402]],"c":true}]},{"i":{"x":0.833,"y":0.833},"o":{"x":0.167,"y":0.167},"t":60,"s":[{"i":[[14.256,-0.77],[0,0],[-0.77,-14.256],[0,0],[-17.407,0.941],[0.941,17.407],[0,0]],"o":[[0,0],[-14.256,0.77],[0,0],[0.941,17.407],[17.407,-0.941],[0,0],[-0.77,-14.256]],"v":[[1.364,-65.982],[-10.046,-65.365],[-34.465,-38.157],[-33.188,-14.524],[0.034,15.291],[29.85,-17.93],[28.573,-41.563]],"c":true}]},{"i":{"x":0.667,"y":1},"o":{"x":0.167,"y":0.167},"t":85,"s":[{"i":[[14.272,-2.552],[0,0],[-2.552,-14.272],[0,0],[-17.426,3.116],[3.116,17.426],[0,0]],"o":[[0,0],[-14.272,2.552],[0,0],[3.116,17.426],[17.426,-3.116],[0,0],[-2.552,-14.272]],"v":[[-8.645,-66.863],[-20.068,-64.82],[-41.287,-34.358],[-37.057,-10.7],[0.138,15.208],[26.048,-21.986],[21.817,-45.643]],"c":true}]},{"t":110,"s":[{"i":[[14.498,0],[0,0],[0,-14.498],[0,0],[-17.702,0],[0,17.702],[0,0]],"o":[[0,0],[-14.498,0],[0,0],[0,17.702],[17.702,0],[0,0],[0,-14.498]],"v":[[5.802,-66.995],[-5.802,-66.995],[-32.053,-40.744],[-32.053,-16.711],[0,15.341],[32.053,-16.711],[32.053,-40.744]],"c":true}]}],"ix":2},"nm":"Trazado 1","mn":"ADBE Vector Shape - Group","hd":false},{"ind":1,"ty":"sh","ix":2,"ks":{"a":1,"k":[{"i":{"x":0.833,"y":0.833},"o":{"x":0.333,"y":0},"t":5,"s":[{"i":[[0,0],[0,-23.64],[0,0],[0,0],[0,0],[22.873,2.836]],"o":[[-22.873,2.836],[0,0],[0,0],[0,0],[0,-23.64],[0,0]],"v":[[-18.267,9.621],[-58.848,55.588],[-58.848,66.995],[58.848,66.995],[58.848,55.588],[18.267,9.621]],"c":false}]},{"i":{"x":0.833,"y":0.833},"o":{"x":0.167,"y":0.167},"t":20,"s":[{"i":[[0,0],[0,-23.64],[0,0],[0,0],[0,0],[22.271,2.7]],"o":[[-22.952,-0.138],[0,0],[0,0],[0,0],[0,-23.64],[0,0]],"v":[[-17.421,7.422],[-58.848,55.588],[-58.848,66.995],[58.848,66.995],[58.848,55.588],[18.656,12.116]],"c":false}]},{"i":{"x":0.833,"y":0.833},"o":{"x":0.167,"y":0.167},"t":45,"s":[{"i":[[0,0],[0,-23.64],[0,0],[0,0],[0,0],[21.97,2.632]],"o":[[-22.991,-1.625],[0,0],[0,0],[0,0],[0,-23.64],[0,0]],"v":[[-16.998,6.323],[-58.848,55.588],[-58.848,66.995],[58.848,66.995],[58.848,55.588],[18.851,13.363]],"c":false}]},{"i":{"x":0.833,"y":0.833},"o":{"x":0.167,"y":0.167},"t":60,"s":[{"i":[[0,0],[0,-23.64],[0,0],[0,0],[0,0],[22.667,0.054]],"o":[[-24.216,0.592],[0,0],[0,0],[0,0],[0,-23.64],[0,0]],"v":[[-18.233,10.637],[-58.848,55.588],[-58.848,66.995],[58.848,66.995],[58.848,55.588],[17.692,8.696]],"c":false}]},{"i":{"x":0.667,"y":1},"o":{"x":0.167,"y":0.167},"t":85,"s":[{"i":[[0,0],[0,-23.64],[0,0],[0,0],[0,0],[23.015,-1.235]],"o":[[-24.828,1.701],[0,0],[0,0],[0,0],[0,-23.64],[0,0]],"v":[[-18.85,12.793],[-58.848,55.588],[-58.848,66.995],[58.848,66.995],[58.848,55.588],[17.113,6.362]],"c":false}]},{"t":110,"s":[{"i":[[0,0],[0,-23.64],[0,0],[0,0],[0,0],[22.873,2.836]],"o":[[-22.873,2.836],[0,0],[0,0],[0,0],[0,-23.64],[0,0]],"v":[[-18.267,9.621],[-58.848,55.588],[-58.848,66.995],[58.848,66.995],[58.848,55.588],[18.267,9.621]],"c":false}]}],"ix":2},"nm":"Trazado 2","mn":"ADBE Vector Shape - Group","hd":false},{"ind":2,"ty":"sh","ix":3,"ks":{"a":1,"k":[{"i":{"x":0.833,"y":0.833},"o":{"x":0.333,"y":0},"t":5,"s":[{"i":[[0,0],[0,0],[0,0],[0,0],[0,0]],"o":[[0,0],[0,0],[0,0],[0,0],[0,0]],"v":[[-32.053,-28.637],[-5.931,-28.637],[0,-36.967],[5.931,-28.637],[32.053,-28.637]],"c":false}]},{"i":{"x":0.833,"y":0.833},"o":{"x":0.167,"y":0.167},"t":20,"s":[{"i":[[0,0],[0,0],[0,0],[0,0],[0,0]],"o":[[0,0],[0,0],[0,0],[0,0],[0,0]],"v":[[-26.12,-32.129],[-3.991,-29.773],[2.936,-37.237],[7.722,-28.249],[37.185,-23.893]],"c":false}]},{"i":{"x":0.833,"y":0.833},"o":{"x":0.167,"y":0.167},"t":45,"s":[{"i":[[0,0],[0,0],[0,0],[0,0],[0,0]],"o":[[0,0],[0,0],[0,0],[0,0],[0,0]],"v":[[-23.154,-33.874],[-3.021,-30.341],[4.404,-37.372],[8.618,-28.055],[39.751,-21.522]],"c":false}]},{"i":{"x":0.833,"y":0.833},"o":{"x":0.167,"y":0.167},"t":60,"s":[{"i":[[0,0],[0,0],[0,0],[0,0],[0,0]],"o":[[0,0],[0,0],[0,0],[0,0],[0,0]],"v":[[-33.822,-26.251],[-5.969,-29.139],[-0.579,-37.646],[5.696,-29.77],[29.216,-29.658]],"c":false}]},{"i":{"x":0.667,"y":1},"o":{"x":0.167,"y":0.167},"t":85,"s":[{"i":[[0,0],[0,0],[0,0],[0,0],[0,0]],"o":[[0,0],[0,0],[0,0],[0,0],[0,0]],"v":[[-39.156,-22.44],[-7.442,-28.539],[-3.07,-37.783],[4.235,-30.627],[23.949,-33.726]],"c":false}]},{"t":110,"s":[{"i":[[0,0],[0,0],[0,0],[0,0],[0,0]],"o":[[0,0],[0,0],[0,0],[0,0],[0,0]],"v":[[-32.053,-28.637],[-5.931,-28.637],[0,-36.967],[5.931,-28.637],[32.053,-28.637]],"c":false}]}],"ix":2},"nm":"Trazado 3","mn":"ADBE Vector Shape - Group","hd":false},{"ty":"mm","mm":1,"nm":"Combinar trazados 1","mn":"ADBE Vector Filter - Merge","hd":false},{"ty":"st","c":{"a":0,"k":[0.20000001496,0.800000059838,0.800000059838,1],"ix":3,"x":"var $bm_rt;\n$bm_rt = thisComp.layer('Main Stroke width - Color Ctrl').effect('Highlight')('ADBE Color Control-0001');"},"o":{"a":0,"k":100,"ix":4},"w":{"a":0,"k":15.4,"ix":5,"x":"var $bm_rt;\n$bm_rt = thisComp.layer('Main Stroke width - Color Ctrl').effect('Stroke width')('ADBE Slider Control-0001');"},"lc":1,"lj":2,"bm":0,"nm":"Trazo 1","mn":"ADBE Vector Graphic - Stroke","hd":false},{"ty":"tr","p":{"a":0,"k":[97.348,105.495],"ix":2},"a":{"a":0,"k":[0,0],"ix":1},"s":{"a":0,"k":[100,100],"ix":3},"r":{"a":0,"k":0,"ix":6},"o":{"a":0,"k":100,"ix":7},"sk":{"a":0,"k":0,"ix":4},"sa":{"a":0,"k":0,"ix":5},"nm":"Transformar"}],"nm":"Grupo 1","np":5,"cix":2,"bm":0,"ix":1,"mn":"ADBE Vector Group","hd":false}],"ip":0,"op":115,"st":0,"bm":0},{"ddd":0,"ind":3,"ty":4,"nm":"Child mask 1","td":1,"sr":1,"ks":{"o":{"a":0,"k":100,"ix":11},"r":{"a":0,"k":0,"ix":10},"p":{"a":0,"k":[260.678,360.506,0],"ix":2,"l":2},"a":{"a":0,"k":[97.348,105.495,0],"ix":1,"l":2},"s":{"a":0,"k":[100,100,100],"ix":6,"l":2}},"ao":0,"shapes":[{"ty":"gr","it":[{"ind":0,"ty":"sh","ix":1,"ks":{"a":1,"k":[{"i":{"x":0.833,"y":0.833},"o":{"x":0.333,"y":0},"t":5,"s":[{"i":[[14.498,0],[0,0],[0,-14.498],[0,0],[-17.702,0],[0,17.702],[0,0]],"o":[[0,0],[-14.498,0],[0,0],[0,17.702],[17.702,0],[0,0],[0,-14.498]],"v":[[5.802,-66.995],[-5.802,-66.995],[-32.053,-40.744],[-32.053,-16.711],[0,15.341],[32.053,-16.711],[32.053,-40.744]],"c":true}]},{"i":{"x":0.833,"y":0.833},"o":{"x":0.167,"y":0.167},"t":20,"s":[{"i":[[14.317,1.862],[0,0],[1.862,-14.317],[0,0],[-17.481,-2.274],[-2.274,17.481],[0,0]],"o":[[0,0],[-14.317,-1.862],[0,0],[-2.274,17.481],[17.481,2.274],[0,0],[1.862,-14.317]],"v":[[16.189,-65.144],[4.73,-66.635],[-24.565,-44.084],[-27.652,-20.352],[-0.117,15.418],[35.653,-12.116],[38.74,-35.849]],"c":true}]},{"i":{"x":0.833,"y":0.833},"o":{"x":0.167,"y":0.167},"t":45,"s":[{"i":[[14.226,2.794],[0,0],[2.794,-14.226],[0,0],[-17.37,-3.411],[-3.411,17.37],[0,0]],"o":[[0,0],[-14.226,-2.794],[0,0],[-3.411,17.37],[17.37,3.411],[0,0],[2.794,-14.226]],"v":[[21.383,-64.219],[9.996,-66.455],[-20.821,-45.754],[-25.452,-22.172],[-0.176,15.456],[37.453,-9.819],[42.084,-33.402]],"c":true}]},{"i":{"x":0.833,"y":0.833},"o":{"x":0.167,"y":0.167},"t":60,"s":[{"i":[[14.256,-0.77],[0,0],[-0.77,-14.256],[0,0],[-17.407,0.941],[0.941,17.407],[0,0]],"o":[[0,0],[-14.256,0.77],[0,0],[0.941,17.407],[17.407,-0.941],[0,0],[-0.77,-14.256]],"v":[[1.364,-65.982],[-10.046,-65.365],[-34.465,-38.157],[-33.188,-14.524],[0.034,15.291],[29.85,-17.93],[28.573,-41.563]],"c":true}]},{"i":{"x":0.667,"y":1},"o":{"x":0.167,"y":0.167},"t":85,"s":[{"i":[[14.272,-2.552],[0,0],[-2.552,-14.272],[0,0],[-17.426,3.116],[3.116,17.426],[0,0]],"o":[[0,0],[-14.272,2.552],[0,0],[3.116,17.426],[17.426,-3.116],[0,0],[-2.552,-14.272]],"v":[[-8.645,-66.863],[-20.068,-64.82],[-41.287,-34.358],[-37.057,-10.7],[0.138,15.208],[26.048,-21.986],[21.817,-45.643]],"c":true}]},{"t":110,"s":[{"i":[[14.498,0],[0,0],[0,-14.498],[0,0],[-17.702,0],[0,17.702],[0,0]],"o":[[0,0],[-14.498,0],[0,0],[0,17.702],[17.702,0],[0,0],[0,-14.498]],"v":[[5.802,-66.995],[-5.802,-66.995],[-32.053,-40.744],[-32.053,-16.711],[0,15.341],[32.053,-16.711],[32.053,-40.744]],"c":true}]}],"ix":2},"nm":"Trazado 1","mn":"ADBE Vector Shape - Group","hd":false},{"ind":1,"ty":"sh","ix":2,"ks":{"a":1,"k":[{"i":{"x":0.833,"y":0.833},"o":{"x":0.333,"y":0},"t":5,"s":[{"i":[[0,0],[0,-23.64],[0,0],[0,0],[0,0],[22.873,2.836]],"o":[[-22.873,2.836],[0,0],[0,0],[0,0],[0,-23.64],[0,0]],"v":[[-18.267,9.621],[-58.848,55.588],[-58.848,66.995],[58.848,66.995],[58.848,55.588],[18.267,9.621]],"c":false}]},{"i":{"x":0.833,"y":0.833},"o":{"x":0.167,"y":0.167},"t":20,"s":[{"i":[[0,0],[0,-23.64],[0,0],[0,0],[0,0],[22.271,2.7]],"o":[[-22.952,-0.138],[0,0],[0,0],[0,0],[0,-23.64],[0,0]],"v":[[-17.421,7.422],[-58.848,55.588],[-58.848,66.995],[58.848,66.995],[58.848,55.588],[18.656,12.116]],"c":false}]},{"i":{"x":0.833,"y":0.833},"o":{"x":0.167,"y":0.167},"t":45,"s":[{"i":[[0,0],[0,-23.64],[0,0],[0,0],[0,0],[21.97,2.632]],"o":[[-22.991,-1.625],[0,0],[0,0],[0,0],[0,-23.64],[0,0]],"v":[[-16.998,6.323],[-58.848,55.588],[-58.848,66.995],[58.848,66.995],[58.848,55.588],[18.851,13.363]],"c":false}]},{"i":{"x":0.833,"y":0.833},"o":{"x":0.167,"y":0.167},"t":60,"s":[{"i":[[0,0],[0,-23.64],[0,0],[0,0],[0,0],[22.667,0.054]],"o":[[-24.216,0.592],[0,0],[0,0],[0,0],[0,-23.64],[0,0]],"v":[[-18.233,10.637],[-58.848,55.588],[-58.848,66.995],[58.848,66.995],[58.848,55.588],[17.692,8.696]],"c":false}]},{"i":{"x":0.667,"y":1},"o":{"x":0.167,"y":0.167},"t":85,"s":[{"i":[[0,0],[0,-23.64],[0,0],[0,0],[0,0],[23.015,-1.235]],"o":[[-24.828,1.701],[0,0],[0,0],[0,0],[0,-23.64],[0,0]],"v":[[-18.85,12.793],[-58.848,55.588],[-58.848,66.995],[58.848,66.995],[58.848,55.588],[17.113,6.362]],"c":false}]},{"t":110,"s":[{"i":[[0,0],[0,-23.64],[0,0],[0,0],[0,0],[22.873,2.836]],"o":[[-22.873,2.836],[0,0],[0,0],[0,0],[0,-23.64],[0,0]],"v":[[-18.267,9.621],[-58.848,55.588],[-58.848,66.995],[58.848,66.995],[58.848,55.588],[18.267,9.621]],"c":false}]}],"ix":2},"nm":"Trazado 2","mn":"ADBE Vector Shape - Group","hd":false},{"ty":"mm","mm":1,"nm":"Combinar trazados 1","mn":"ADBE Vector Filter - Merge","hd":false},{"ty":"fl","c":{"a":0,"k":[1,0,0,1],"ix":4},"o":{"a":0,"k":100,"ix":5},"r":1,"bm":0,"nm":"Relleno 1","mn":"ADBE Vector Graphic - Fill","hd":false},{"ty":"tr","p":{"a":0,"k":[97.348,105.495],"ix":2},"a":{"a":0,"k":[0,0],"ix":1},"s":{"a":0,"k":[100,100],"ix":3},"r":{"a":0,"k":0,"ix":6},"o":{"a":0,"k":100,"ix":7},"sk":{"a":0,"k":0,"ix":4},"sa":{"a":0,"k":0,"ix":5},"nm":"Transformar"}],"nm":"Grupo 1","np":4,"cix":2,"bm":0,"ix":1,"mn":"ADBE Vector Group","hd":false}],"ip":0,"op":115,"st":0,"bm":0},{"ddd":0,"ind":4,"ty":4,"nm":"Man ","tt":2,"sr":1,"ks":{"o":{"a":0,"k":100,"ix":11},"r":{"a":0,"k":0,"ix":10},"p":{"a":1,"k":[{"i":{"x":0.833,"y":0.936},"o":{"x":0.333,"y":0},"t":5,"s":[158.555,292.021,0],"to":[0,0,0],"ti":[0,0,0]},{"i":{"x":0.833,"y":0.636},"o":{"x":0.167,"y":0.32},"t":20,"s":[165.15,292.021,0],"to":[0,0,0],"ti":[0,0,0]},{"i":{"x":0.667,"y":1},"o":{"x":0.167,"y":0.088},"t":70,"s":[169.555,292.021,0],"to":[0,0,0],"ti":[0,0,0]},{"t":100,"s":[158.555,292.021,0]}],"ix":2,"l":2},"a":{"a":0,"k":[112.555,173.979,0],"ix":1,"l":2},"s":{"a":0,"k":[100,100,100],"ix":6,"l":2}},"ao":0,"shapes":[{"ty":"gr","it":[{"ind":0,"ty":"sh","ix":1,"ks":{"a":0,"k":{"i":[[0,0],[0,0]],"o":[[0,0],[0,0]],"v":[[-29.837,79.137],[-29.837,135.479]],"c":false},"ix":2},"nm":"Trazado 1","mn":"ADBE Vector Shape - Group","hd":false},{"ind":1,"ty":"sh","ix":2,"ks":{"a":1,"k":[{"i":{"x":0.833,"y":0.833},"o":{"x":0.333,"y":0},"t":5,"s":[{"i":[[-11.118,0],[0,0],[18.892,0],[0,0],[0,-18.892],[0,0],[-20.521,8.795]],"o":[[0,0],[0,-18.892],[0,0],[-18.892,0],[0,0],[23.74,0],[6.163,8.282]],"v":[[66.908,-75.949],[66.908,-101.272],[32.701,-135.479],[7.14,-135.479],[-27.067,-101.272],[-27.067,-75.949],[39.793,-89.621]],"c":true}]},{"i":{"x":0.833,"y":0.833},"o":{"x":0.167,"y":0.167},"t":20,"s":[{"i":[[-4.382,-0.071],[0,0],[18.892,0],[0,0],[0,-18.892],[0,0],[-20.521,8.795]],"o":[[0,0],[0,-18.892],[0,0],[-18.892,0],[0,0],[23.74,0],[3.733,7.681]],"v":[[66.828,-72.449],[66.828,-97.772],[32.621,-131.979],[7.06,-131.979],[-27.147,-97.772],[-27.147,-72.449],[47.713,-86.202]],"c":true}]},{"i":{"x":0.833,"y":0.833},"o":{"x":0.167,"y":0.167},"t":30,"s":[{"i":[[-4.382,-0.071],[0,0],[18.892,0],[0,0],[0,-18.892],[0,0],[-20.521,8.795]],"o":[[0,0],[0,-18.892],[0,0],[-18.892,0],[0,0],[23.74,0],[3.733,7.681]],"v":[[66.68,-75.949],[66.68,-101.272],[32.473,-135.479],[6.912,-135.479],[-27.295,-101.272],[-27.295,-75.949],[47.565,-89.702]],"c":true}]},{"i":{"x":0.833,"y":0.833},"o":{"x":0.167,"y":0.167},"t":40,"s":[{"i":[[-4.382,-0.071],[0,0],[18.892,0],[0,0],[0,-18.892],[0,0],[-20.521,8.795]],"o":[[0,0],[0,-18.892],[0,0],[-18.892,0],[0,0],[23.74,0],[3.733,7.681]],"v":[[66.828,-72.449],[66.828,-97.772],[32.621,-131.979],[7.06,-131.979],[-27.147,-97.772],[-27.147,-72.449],[47.713,-86.202]],"c":true}]},{"i":{"x":0.833,"y":0.833},"o":{"x":0.167,"y":0.167},"t":50,"s":[{"i":[[-4.382,-0.071],[0,0],[18.892,0],[0,0],[0,-18.892],[0,0],[-20.521,8.795]],"o":[[0,0],[0,-18.892],[0,0],[-18.892,0],[0,0],[23.74,0],[3.733,7.681]],"v":[[66.68,-75.949],[66.68,-101.272],[32.473,-135.479],[6.912,-135.479],[-27.295,-101.272],[-27.295,-75.949],[47.565,-89.702]],"c":true}]},{"i":{"x":0.833,"y":0.833},"o":{"x":0.167,"y":0.167},"t":60,"s":[{"i":[[-4.382,-0.071],[0,0],[18.892,0],[0,0],[0,-18.892],[0,0],[-20.521,8.795]],"o":[[0,0],[0,-18.892],[0,0],[-18.892,0],[0,0],[23.74,0],[3.733,7.681]],"v":[[66.828,-72.449],[66.828,-97.772],[32.621,-131.979],[7.06,-131.979],[-27.147,-97.772],[-27.147,-72.449],[47.713,-86.202]],"c":true}]},{"i":{"x":0.667,"y":1},"o":{"x":0.167,"y":0.167},"t":70,"s":[{"i":[[-4.382,-0.071],[0,0],[18.892,0],[0,0],[0,-18.892],[0,0],[-20.521,8.795]],"o":[[0,0],[0,-18.892],[0,0],[-18.892,0],[0,0],[23.74,0],[3.733,7.681]],"v":[[66.68,-75.949],[66.68,-101.272],[32.473,-135.479],[6.912,-135.479],[-27.295,-101.272],[-27.295,-75.949],[47.565,-89.702]],"c":true}]},{"t":90,"s":[{"i":[[-11.118,0],[0,0],[18.892,0],[0,0],[0,-18.892],[0,0],[-20.521,8.795]],"o":[[0,0],[0,-18.892],[0,0],[-18.892,0],[0,0],[23.74,0],[6.163,8.282]],"v":[[66.908,-75.949],[66.908,-101.272],[32.701,-135.479],[7.14,-135.479],[-27.067,-101.272],[-27.067,-75.949],[39.793,-89.621]],"c":true}]}],"ix":2},"nm":"Trazado 2","mn":"ADBE Vector Shape - Group","hd":false},{"ind":2,"ty":"sh","ix":3,"ks":{"a":1,"k":[{"i":{"x":0.833,"y":0.833},"o":{"x":0.333,"y":0},"t":5,"s":[{"i":[[0,0],[0,0],[-25.95,0],[0,0],[0,25.95],[0,0]],"o":[[0,0],[0,25.95],[0,0],[25.95,0],[0,0],[0,0]],"v":[[-27.067,-86.294],[-27.067,-53.026],[19.92,-6.04],[19.921,-6.04],[66.908,-53.026],[66.908,-86.294]],"c":false}]},{"i":{"x":0.833,"y":0.833},"o":{"x":0.167,"y":0.167},"t":20,"s":[{"i":[[0,0],[0,0],[-25.95,0],[0,0],[0,25.95],[0,0]],"o":[[0,0],[0,25.95],[0,0],[25.95,0],[0,0],[0,0]],"v":[[-27.147,-82.794],[-27.147,-49.526],[19.84,-2.54],[19.841,-2.54],[66.828,-49.526],[66.828,-82.794]],"c":false}]},{"i":{"x":0.833,"y":0.833},"o":{"x":0.167,"y":0.167},"t":30,"s":[{"i":[[0,0],[0,0],[-25.95,0],[0,0],[0,25.95],[0,0]],"o":[[0,0],[0,25.95],[0,0],[25.95,0],[0,0],[0,0]],"v":[[-27.295,-86.294],[-27.295,-53.026],[19.692,-6.04],[19.693,-6.04],[66.68,-53.026],[66.68,-86.294]],"c":false}]},{"i":{"x":0.833,"y":0.833},"o":{"x":0.167,"y":0.167},"t":40,"s":[{"i":[[0,0],[0,0],[-25.95,0],[0,0],[0,25.95],[0,0]],"o":[[0,0],[0,25.95],[0,0],[25.95,0],[0,0],[0,0]],"v":[[-27.147,-82.794],[-27.147,-49.526],[19.84,-2.54],[19.841,-2.54],[66.828,-49.526],[66.828,-82.794]],"c":false}]},{"i":{"x":0.833,"y":0.833},"o":{"x":0.167,"y":0.167},"t":50,"s":[{"i":[[0,0],[0,0],[-25.95,0],[0,0],[0,25.95],[0,0]],"o":[[0,0],[0,25.95],[0,0],[25.95,0],[0,0],[0,0]],"v":[[-27.295,-86.294],[-27.295,-53.026],[19.692,-6.04],[19.693,-6.04],[66.68,-53.026],[66.68,-86.294]],"c":false}]},{"i":{"x":0.833,"y":0.833},"o":{"x":0.167,"y":0.167},"t":60,"s":[{"i":[[0,0],[0,0],[-25.95,0],[0,0],[0,25.95],[0,0]],"o":[[0,0],[0,25.95],[0,0],[25.95,0],[0,0],[0,0]],"v":[[-27.147,-82.794],[-27.147,-49.526],[19.84,-2.54],[19.841,-2.54],[66.828,-49.526],[66.828,-82.794]],"c":false}]},{"i":{"x":0.667,"y":1},"o":{"x":0.167,"y":0.167},"t":70,"s":[{"i":[[0,0],[0,0],[-25.95,0],[0,0],[0,25.95],[0,0]],"o":[[0,0],[0,25.95],[0,0],[25.95,0],[0,0],[0,0]],"v":[[-27.295,-86.294],[-27.295,-53.026],[19.692,-6.04],[19.693,-6.04],[66.68,-53.026],[66.68,-86.294]],"c":false}]},{"t":90,"s":[{"i":[[0,0],[0,0],[-25.95,0],[0,0],[0,25.95],[0,0]],"o":[[0,0],[0,25.95],[0,0],[25.95,0],[0,0],[0,0]],"v":[[-27.067,-86.294],[-27.067,-53.026],[19.92,-6.04],[19.921,-6.04],[66.908,-53.026],[66.908,-86.294]],"c":false}]}],"ix":2},"nm":"Trazado 3","mn":"ADBE Vector Shape - Group","hd":false},{"ind":3,"ty":"sh","ix":4,"ks":{"a":1,"k":[{"i":{"x":0.833,"y":0.833},"o":{"x":0.333,"y":0},"t":5,"s":[{"i":[[0,0],[0,0],[-9.682,0],[0,9.682],[0,0]],"o":[[0,0],[0,9.682],[9.683,0],[0,0],[0,0]],"v":[[2.389,-8.495],[2.389,10.303],[19.92,27.833],[37.452,10.303],[37.452,-8.495]],"c":false}]},{"i":{"x":0.833,"y":0.833},"o":{"x":0.167,"y":0.167},"t":20,"s":[{"i":[[0,0],[0,0],[-9.682,0],[0,9.682],[0,0]],"o":[[0,0],[0,9.682],[9.683,0],[0,0],[0,0]],"v":[[2.309,-4.995],[2.389,10.303],[19.92,27.833],[37.452,10.303],[37.372,-4.995]],"c":false}]},{"i":{"x":0.833,"y":0.833},"o":{"x":0.167,"y":0.167},"t":30,"s":[{"i":[[0,0],[0,0],[-9.682,0],[0,9.682],[0,0]],"o":[[0,0],[0,9.682],[9.683,0],[0,0],[0,0]],"v":[[2.161,-8.495],[2.389,10.303],[19.92,27.833],[37.452,10.303],[37.224,-8.495]],"c":false}]},{"i":{"x":0.833,"y":0.833},"o":{"x":0.167,"y":0.167},"t":40,"s":[{"i":[[0,0],[0,0],[-9.682,0],[0,9.682],[0,0]],"o":[[0,0],[0,9.682],[9.683,0],[0,0],[0,0]],"v":[[2.309,-4.995],[2.389,10.303],[19.92,27.833],[37.452,10.303],[37.372,-4.995]],"c":false}]},{"i":{"x":0.833,"y":0.833},"o":{"x":0.167,"y":0.167},"t":50,"s":[{"i":[[0,0],[0,0],[-9.682,0],[0,9.682],[0,0]],"o":[[0,0],[0,9.682],[9.683,0],[0,0],[0,0]],"v":[[2.161,-8.495],[2.389,10.303],[19.92,27.833],[37.452,10.303],[37.224,-8.495]],"c":false}]},{"i":{"x":0.833,"y":0.833},"o":{"x":0.167,"y":0.167},"t":60,"s":[{"i":[[0,0],[0,0],[-9.682,0],[0,9.682],[0,0]],"o":[[0,0],[0,9.682],[9.683,0],[0,0],[0,0]],"v":[[2.309,-4.995],[2.389,10.303],[19.92,27.833],[37.452,10.303],[37.372,-4.995]],"c":false}]},{"i":{"x":0.667,"y":1},"o":{"x":0.167,"y":0.167},"t":70,"s":[{"i":[[0,0],[0,0],[-9.682,0],[0,9.682],[0,0]],"o":[[0,0],[0,9.682],[9.683,0],[0,0],[0,0]],"v":[[2.161,-8.495],[2.389,10.303],[19.92,27.833],[37.452,10.303],[37.224,-8.495]],"c":false}]},{"t":90,"s":[{"i":[[0,0],[0,0],[-9.682,0],[0,9.682],[0,0]],"o":[[0,0],[0,9.682],[9.683,0],[0,0],[0,0]],"v":[[2.389,-8.495],[2.389,10.303],[19.92,27.833],[37.452,10.303],[37.452,-8.495]],"c":false}]}],"ix":2},"nm":"Trazado 4","mn":"ADBE Vector Shape - Group","hd":false},{"ind":4,"ty":"sh","ix":5,"ks":{"a":1,"k":[{"i":{"x":0.833,"y":0.833},"o":{"x":0.333,"y":0},"t":5,"s":[{"i":[[0,0],[13.059,0]],"o":[[-10.731,-5.808],[0,0]],"v":[[74.055,13.842],[37.977,4.736]],"c":false}]},{"i":{"x":0.833,"y":0.833},"o":{"x":0.167,"y":0.167},"t":20,"s":[{"i":[[0,0],[15.968,-4.757]],"o":[[-6.11,-6.363],[0,0]],"v":[[74.055,13.842],[37.977,4.736]],"c":false}]},{"i":{"x":0.833,"y":0.833},"o":{"x":0.167,"y":0.167},"t":30,"s":[{"i":[[0,0],[13.059,0]],"o":[[-10.731,-5.808],[0,0]],"v":[[74.055,13.842],[37.977,4.736]],"c":false}]},{"i":{"x":0.833,"y":0.833},"o":{"x":0.167,"y":0.167},"t":40,"s":[{"i":[[0,0],[15.968,-4.757]],"o":[[-6.11,-6.363],[0,0]],"v":[[74.055,13.842],[37.977,4.736]],"c":false}]},{"i":{"x":0.833,"y":0.833},"o":{"x":0.167,"y":0.167},"t":50,"s":[{"i":[[0,0],[13.059,0]],"o":[[-10.731,-5.808],[0,0]],"v":[[74.055,13.842],[37.977,4.736]],"c":false}]},{"i":{"x":0.667,"y":1},"o":{"x":0.167,"y":0.167},"t":60,"s":[{"i":[[0,0],[15.968,-4.757]],"o":[[-6.11,-6.363],[0,0]],"v":[[74.055,13.842],[37.977,4.736]],"c":false}]},{"t":70,"s":[{"i":[[0,0],[13.059,0]],"o":[[-10.731,-5.808],[0,0]],"v":[[74.055,13.842],[37.977,4.736]],"c":false}]}],"ix":2},"nm":"Trazado 5","mn":"ADBE Vector Shape - Group","hd":false},{"ind":5,"ty":"sh","ix":6,"ks":{"a":1,"k":[{"i":{"x":0.833,"y":0.833},"o":{"x":0.333,"y":0},"t":5,"s":[{"i":[[0,0],[0,0],[0,0],[-41.929,0]],"o":[[0,0],[0,0],[0,-41.929],[0,0]],"v":[[43.276,135.479],[-74.055,135.479],[-74.055,80.656],[1.864,4.736]],"c":false}]},{"i":{"x":0.833,"y":0.833},"o":{"x":0.167,"y":0.167},"t":20,"s":[{"i":[[0,0],[0,0],[0,0],[-48.919,-12.257]],"o":[[0,0],[0,0],[-0.5,-44.676],[0,0]],"v":[[43.276,135.479],[-74.055,135.479],[-74.055,80.656],[1.864,4.736]],"c":false}]},{"i":{"x":0.833,"y":0.833},"o":{"x":0.167,"y":0.167},"t":30,"s":[{"i":[[0,0],[0,0],[0,0],[-41.929,0]],"o":[[0,0],[0,0],[0,-41.929],[0,0]],"v":[[43.276,135.479],[-74.055,135.479],[-74.055,80.656],[1.864,4.736]],"c":false}]},{"i":{"x":0.833,"y":0.833},"o":{"x":0.167,"y":0.167},"t":40,"s":[{"i":[[0,0],[0,0],[0,0],[-48.919,-12.257]],"o":[[0,0],[0,0],[-0.5,-44.676],[0,0]],"v":[[43.276,135.479],[-74.055,135.479],[-74.055,80.656],[1.864,4.736]],"c":false}]},{"i":{"x":0.833,"y":0.833},"o":{"x":0.167,"y":0.167},"t":50,"s":[{"i":[[0,0],[0,0],[0,0],[-41.929,0]],"o":[[0,0],[0,0],[0,-41.929],[0,0]],"v":[[43.276,135.479],[-74.055,135.479],[-74.055,80.656],[1.864,4.736]],"c":false}]},{"i":{"x":0.667,"y":1},"o":{"x":0.167,"y":0.167},"t":60,"s":[{"i":[[0,0],[0,0],[0,0],[-48.919,-12.257]],"o":[[0,0],[0,0],[-0.5,-44.676],[0,0]],"v":[[43.276,135.479],[-74.055,135.479],[-74.055,80.656],[1.864,4.736]],"c":false}]},{"t":70,"s":[{"i":[[0,0],[0,0],[0,0],[-41.929,0]],"o":[[0,0],[0,0],[0,-41.929],[0,0]],"v":[[43.276,135.479],[-74.055,135.479],[-74.055,80.656],[1.864,4.736]],"c":false}]}],"ix":2},"nm":"Trazado 6","mn":"ADBE Vector Shape - Group","hd":false},{"ty":"mm","mm":1,"nm":"Combinar trazados 1","mn":"ADBE Vector Filter - Merge","hd":false},{"ty":"st","c":{"a":0,"k":[0,0,0,1],"ix":3,"x":"var $bm_rt;\n$bm_rt = thisComp.layer('Main Stroke width - Color Ctrl').effect('Base Color')('ADBE Color Control-0001');"},"o":{"a":0,"k":100,"ix":4},"w":{"a":0,"k":15.4,"ix":5,"x":"var $bm_rt;\n$bm_rt = thisComp.layer('Main Stroke width - Color Ctrl').effect('Stroke width')('ADBE Slider Control-0001');"},"lc":2,"lj":2,"bm":0,"nm":"Trazo 1","mn":"ADBE Vector Graphic - Stroke","hd":false},{"ty":"tr","p":{"a":0,"k":[112.555,173.979],"ix":2},"a":{"a":0,"k":[0,0],"ix":1},"s":{"a":0,"k":[100,100],"ix":3},"r":{"a":0,"k":0,"ix":6},"o":{"a":0,"k":100,"ix":7},"sk":{"a":0,"k":0,"ix":4},"sa":{"a":0,"k":0,"ix":5},"nm":"Transformar"}],"nm":"Grupo 1","np":8,"cix":2,"bm":0,"ix":1,"mn":"ADBE Vector Group","hd":false}],"ip":0,"op":115,"st":0,"bm":0},{"ddd":0,"ind":5,"ty":4,"nm":"Child mask 2","td":1,"sr":1,"ks":{"o":{"a":0,"k":100,"ix":11},"r":{"a":0,"k":0,"ix":10},"p":{"a":0,"k":[260.678,360.506,0],"ix":2,"l":2},"a":{"a":0,"k":[97.348,105.495,0],"ix":1,"l":2},"s":{"a":0,"k":[100,100,100],"ix":6,"l":2}},"ao":0,"shapes":[{"ty":"gr","it":[{"ind":0,"ty":"sh","ix":1,"ks":{"a":1,"k":[{"i":{"x":0.833,"y":0.833},"o":{"x":0.333,"y":0},"t":5,"s":[{"i":[[14.498,0],[0,0],[0,-14.498],[0,0],[-17.702,0],[0,17.702],[0,0]],"o":[[0,0],[-14.498,0],[0,0],[0,17.702],[17.702,0],[0,0],[0,-14.498]],"v":[[5.802,-66.995],[-5.802,-66.995],[-32.053,-40.744],[-32.053,-16.711],[0,15.341],[32.053,-16.711],[32.053,-40.744]],"c":true}]},{"i":{"x":0.833,"y":0.833},"o":{"x":0.167,"y":0.167},"t":20,"s":[{"i":[[14.317,1.862],[0,0],[1.862,-14.317],[0,0],[-17.481,-2.274],[-2.274,17.481],[0,0]],"o":[[0,0],[-14.317,-1.862],[0,0],[-2.274,17.481],[17.481,2.274],[0,0],[1.862,-14.317]],"v":[[16.189,-65.144],[4.73,-66.635],[-24.565,-44.084],[-27.652,-20.352],[-0.117,15.418],[35.653,-12.116],[38.74,-35.849]],"c":true}]},{"i":{"x":0.833,"y":0.833},"o":{"x":0.167,"y":0.167},"t":45,"s":[{"i":[[14.226,2.794],[0,0],[2.794,-14.226],[0,0],[-17.37,-3.411],[-3.411,17.37],[0,0]],"o":[[0,0],[-14.226,-2.794],[0,0],[-3.411,17.37],[17.37,3.411],[0,0],[2.794,-14.226]],"v":[[21.383,-64.219],[9.996,-66.455],[-20.821,-45.754],[-25.452,-22.172],[-0.176,15.456],[37.453,-9.819],[42.084,-33.402]],"c":true}]},{"i":{"x":0.833,"y":0.833},"o":{"x":0.167,"y":0.167},"t":60,"s":[{"i":[[14.256,-0.77],[0,0],[-0.77,-14.256],[0,0],[-17.407,0.941],[0.941,17.407],[0,0]],"o":[[0,0],[-14.256,0.77],[0,0],[0.941,17.407],[17.407,-0.941],[0,0],[-0.77,-14.256]],"v":[[1.364,-65.982],[-10.046,-65.365],[-34.465,-38.157],[-33.188,-14.524],[0.034,15.291],[29.85,-17.93],[28.573,-41.563]],"c":true}]},{"i":{"x":0.667,"y":1},"o":{"x":0.167,"y":0.167},"t":85,"s":[{"i":[[14.272,-2.552],[0,0],[-2.552,-14.272],[0,0],[-17.426,3.116],[3.116,17.426],[0,0]],"o":[[0,0],[-14.272,2.552],[0,0],[3.116,17.426],[17.426,-3.116],[0,0],[-2.552,-14.272]],"v":[[-8.645,-66.863],[-20.068,-64.82],[-41.287,-34.358],[-37.057,-10.7],[0.138,15.208],[26.048,-21.986],[21.817,-45.643]],"c":true}]},{"t":110,"s":[{"i":[[14.498,0],[0,0],[0,-14.498],[0,0],[-17.702,0],[0,17.702],[0,0]],"o":[[0,0],[-14.498,0],[0,0],[0,17.702],[17.702,0],[0,0],[0,-14.498]],"v":[[5.802,-66.995],[-5.802,-66.995],[-32.053,-40.744],[-32.053,-16.711],[0,15.341],[32.053,-16.711],[32.053,-40.744]],"c":true}]}],"ix":2},"nm":"Trazado 1","mn":"ADBE Vector Shape - Group","hd":false},{"ind":1,"ty":"sh","ix":2,"ks":{"a":1,"k":[{"i":{"x":0.833,"y":0.833},"o":{"x":0.333,"y":0},"t":5,"s":[{"i":[[0,0],[0,-23.64],[0,0],[0,0],[0,0],[22.873,2.836]],"o":[[-22.873,2.836],[0,0],[0,0],[0,0],[0,-23.64],[0,0]],"v":[[-18.267,9.621],[-58.848,55.588],[-58.848,66.995],[58.848,66.995],[58.848,55.588],[18.267,9.621]],"c":false}]},{"i":{"x":0.833,"y":0.833},"o":{"x":0.167,"y":0.167},"t":20,"s":[{"i":[[0,0],[0,-23.64],[0,0],[0,0],[0,0],[22.271,2.7]],"o":[[-22.952,-0.138],[0,0],[0,0],[0,0],[0,-23.64],[0,0]],"v":[[-17.421,7.422],[-58.848,55.588],[-58.848,66.995],[58.848,66.995],[58.848,55.588],[18.656,12.116]],"c":false}]},{"i":{"x":0.833,"y":0.833},"o":{"x":0.167,"y":0.167},"t":45,"s":[{"i":[[0,0],[0,-23.64],[0,0],[0,0],[0,0],[21.97,2.632]],"o":[[-22.991,-1.625],[0,0],[0,0],[0,0],[0,-23.64],[0,0]],"v":[[-16.998,6.323],[-58.848,55.588],[-58.848,66.995],[58.848,66.995],[58.848,55.588],[18.851,13.363]],"c":false}]},{"i":{"x":0.833,"y":0.833},"o":{"x":0.167,"y":0.167},"t":60,"s":[{"i":[[0,0],[0,-23.64],[0,0],[0,0],[0,0],[22.667,0.054]],"o":[[-24.216,0.592],[0,0],[0,0],[0,0],[0,-23.64],[0,0]],"v":[[-18.233,10.637],[-58.848,55.588],[-58.848,66.995],[58.848,66.995],[58.848,55.588],[17.692,8.696]],"c":false}]},{"i":{"x":0.667,"y":1},"o":{"x":0.167,"y":0.167},"t":85,"s":[{"i":[[0,0],[0,-23.64],[0,0],[0,0],[0,0],[23.015,-1.235]],"o":[[-24.828,1.701],[0,0],[0,0],[0,0],[0,-23.64],[0,0]],"v":[[-18.85,12.793],[-58.848,55.588],[-58.848,66.995],[58.848,66.995],[58.848,55.588],[17.113,6.362]],"c":false}]},{"t":110,"s":[{"i":[[0,0],[0,-23.64],[0,0],[0,0],[0,0],[22.873,2.836]],"o":[[-22.873,2.836],[0,0],[0,0],[0,0],[0,-23.64],[0,0]],"v":[[-18.267,9.621],[-58.848,55.588],[-58.848,66.995],[58.848,66.995],[58.848,55.588],[18.267,9.621]],"c":false}]}],"ix":2},"nm":"Trazado 2","mn":"ADBE Vector Shape - Group","hd":false},{"ty":"mm","mm":1,"nm":"Combinar trazados 1","mn":"ADBE Vector Filter - Merge","hd":false},{"ty":"fl","c":{"a":0,"k":[1,0,0,1],"ix":4},"o":{"a":0,"k":100,"ix":5},"r":1,"bm":0,"nm":"Relleno 1","mn":"ADBE Vector Graphic - Fill","hd":false},{"ty":"tr","p":{"a":0,"k":[97.348,105.495],"ix":2},"a":{"a":0,"k":[0,0],"ix":1},"s":{"a":0,"k":[100,100],"ix":3},"r":{"a":0,"k":0,"ix":6},"o":{"a":0,"k":100,"ix":7},"sk":{"a":0,"k":0,"ix":4},"sa":{"a":0,"k":0,"ix":5},"nm":"Transformar"}],"nm":"Grupo 1","np":4,"cix":2,"bm":0,"ix":1,"mn":"ADBE Vector Group","hd":false}],"ip":0,"op":115,"st":0,"bm":0},{"ddd":0,"ind":6,"ty":4,"nm":"Woman ","tt":2,"sr":1,"ks":{"o":{"a":0,"k":100,"ix":11},"r":{"a":0,"k":0,"ix":10},"p":{"a":1,"k":[{"i":{"x":0.833,"y":0.936},"o":{"x":0.333,"y":0},"t":5,"s":[359.152,280.67,0],"to":[0,0,0],"ti":[0,0,0]},{"i":{"x":0.833,"y":0.635},"o":{"x":0.167,"y":0.321},"t":20,"s":[350.152,280.67,0],"to":[0,0,0],"ti":[0,0,0]},{"i":{"x":0.667,"y":1},"o":{"x":0.167,"y":0.087},"t":70,"s":[344.152,280.67,0],"to":[0,0,0],"ti":[0,0,0]},{"t":100,"s":[359.152,280.67,0]}],"ix":2,"l":2},"a":{"a":0,"k":[106.848,185.33,0],"ix":1,"l":2},"s":{"a":0,"k":[100,100,100],"ix":6,"l":2}},"ao":0,"shapes":[{"ty":"gr","it":[{"ind":0,"ty":"sh","ix":1,"ks":{"a":1,"k":[{"i":{"x":0.833,"y":0.833},"o":{"x":0.333,"y":0},"t":5,"s":[{"i":[[0,0],[0,0]],"o":[[0,0],[0,0]],"v":[[24.13,90.515],[24.13,146.857]],"c":false}]},{"i":{"x":0.833,"y":0.833},"o":{"x":0.167,"y":0.167},"t":20,"s":[{"i":[[0,0],[0,0]],"o":[[0,0],[0,0]],"v":[[24.13,90.515],[15.213,146.92]],"c":false}]},{"i":{"x":0.667,"y":1},"o":{"x":0.167,"y":0.167},"t":70,"s":[{"i":[[0,0],[0,0]],"o":[[0,0],[0,0]],"v":[[24.13,90.515],[9.268,146.962]],"c":false}]},{"t":100,"s":[{"i":[[0,0],[0,0]],"o":[[0,0],[0,0]],"v":[[24.13,90.515],[24.13,146.857]],"c":false}]}],"ix":2},"nm":"Trazado 1","mn":"ADBE Vector Shape - Group","hd":false},{"ind":1,"ty":"sh","ix":2,"ks":{"a":1,"k":[{"i":{"x":0.833,"y":0.833},"o":{"x":0.333,"y":0},"t":5,"s":[{"i":[[0,0],[0,0],[-21.117,0],[0,21.117],[0,0]],"o":[[0,0],[0,21.117],[21.118,0],[0,0],[0,0]],"v":[[-53.502,-45.785],[-53.502,-24.37],[-15.266,13.867],[22.971,-24.37],[22.971,-45.785]],"c":true}]},{"i":{"x":0.833,"y":0.833},"o":{"x":0.167,"y":0.167},"t":20,"s":[{"i":[[0,0],[0,0],[-20.99,1.788],[1.788,20.99],[0,0]],"o":[[0,0],[1.788,20.99],[20.991,-1.788],[0,0],[0,0]],"v":[[-58.286,-42.267],[-56.473,-20.98],[-15.228,13.789],[19.541,-27.457],[17.727,-48.743]],"c":true}]},{"i":{"x":0.667,"y":1},"o":{"x":0.167,"y":0.167},"t":70,"s":[{"i":[[0,0],[0,0],[-20.906,2.981],[2.981,20.906],[0,0]],"o":[[0,0],[2.981,20.906],[20.907,-2.981],[0,0],[0,0]],"v":[[-61.476,-39.921],[-58.453,-18.72],[-15.203,13.737],[17.254,-29.515],[14.231,-50.715]],"c":true}]},{"t":100,"s":[{"i":[[0,0],[0,0],[-21.117,0],[0,21.117],[0,0]],"o":[[0,0],[0,21.117],[21.118,0],[0,0],[0,0]],"v":[[-53.502,-45.785],[-53.502,-24.37],[-15.266,13.867],[22.971,-24.37],[22.971,-45.785]],"c":true}]}],"ix":2},"nm":"Trazado 2","mn":"ADBE Vector Shape - Group","hd":false},{"ind":2,"ty":"sh","ix":3,"ks":{"a":1,"k":[{"i":{"x":0.833,"y":0.833},"o":{"x":0.333,"y":0},"t":5,"s":[{"i":[[0,0],[0,14.556],[29.317,0],[0,-29.316],[-9.488,-9.59]],"o":[[9.488,-9.59],[0,-29.316],[-29.316,0],[0,14.556],[0,0]],"v":[[22.466,-18.186],[37.817,-55.515],[-15.266,-108.597],[-68.348,-55.515],[-52.997,-18.186]],"c":false}]},{"i":{"x":0.833,"y":0.833},"o":{"x":0.167,"y":0.167},"t":20,"s":[{"i":[[0,0],[1.233,14.469],[29.141,-2.483],[-2.483,-29.14],[-10.243,-8.729]],"o":[[8.619,-10.336],[-2.483,-29.14],[-29.14,2.483],[1.233,14.469],[0,0]],"v":[[19.563,-21.267],[31.66,-59.672],[-25.6,-107.939],[-73.867,-50.681],[-55.447,-14.876]],"c":false}]},{"i":{"x":0.667,"y":1},"o":{"x":0.167,"y":0.167},"t":70,"s":[{"i":[[0,0],[2.055,14.41],[29.023,-4.138],[-4.138,-29.023],[-10.747,-8.155]],"o":[[8.039,-10.833],[-4.138,-29.022],[-29.022,4.138],[2.055,14.41],[0,0]],"v":[[17.627,-23.321],[27.555,-62.443],[-32.489,-107.501],[-77.547,-47.458],[-57.08,-12.67]],"c":false}]},{"t":100,"s":[{"i":[[0,0],[0,14.556],[29.317,0],[0,-29.316],[-9.488,-9.59]],"o":[[9.488,-9.59],[0,-29.316],[-29.316,0],[0,14.556],[0,0]],"v":[[22.466,-18.186],[37.817,-55.515],[-15.266,-108.597],[-68.348,-55.515],[-52.997,-18.186]],"c":false}]}],"ix":2},"nm":"Trazado 3","mn":"ADBE Vector Shape - Group","hd":false},{"ind":3,"ty":"sh","ix":4,"ks":{"a":1,"k":[{"i":{"x":0.833,"y":0.833},"o":{"x":0.333,"y":0},"t":5,"s":[{"i":[[0,0],[0,0],[-8.937,0],[0,8.938],[0,0]],"o":[[0,0],[0,8.938],[8.938,0],[0,0],[0,0]],"v":[[-31.448,10.595],[-31.448,28.539],[-15.266,44.722],[0.917,28.539],[0.917,10.595]],"c":false}]},{"i":{"x":0.833,"y":0.833},"o":{"x":0.167,"y":0.167},"t":20,"s":[{"i":[[0,0],[0,0],[-8.937,0],[0,8.938],[0,0]],"o":[[0,0],[0,8.938],[8.938,0],[0,0],[0,0]],"v":[[-31.59,11.907],[-31.448,28.539],[-15.266,44.722],[0.917,28.539],[0.581,9.166]],"c":false}]},{"i":{"x":0.667,"y":1},"o":{"x":0.167,"y":0.167},"t":70,"s":[{"i":[[0,0],[0,0],[-8.937,0],[0,8.938],[0,0]],"o":[[0,0],[0,8.938],[8.938,0],[0,0],[0,0]],"v":[[-31.685,12.782],[-31.448,28.539],[-15.266,44.722],[0.917,28.539],[0.356,8.213]],"c":false}]},{"t":100,"s":[{"i":[[0,0],[0,0],[-8.937,0],[0,8.938],[0,0]],"o":[[0,0],[0,8.938],[8.938,0],[0,0],[0,0]],"v":[[-31.448,10.595],[-31.448,28.539],[-15.266,44.722],[0.917,28.539],[0.917,10.595]],"c":false}]}],"ix":2},"nm":"Trazado 4","mn":"ADBE Vector Shape - Group","hd":false},{"ind":4,"ty":"sh","ix":5,"ks":{"a":1,"k":[{"i":{"x":0.833,"y":0.833},"o":{"x":0.333,"y":0},"t":5,"s":[{"i":[[0,0],[10.217,-6.711]],"o":[[-12.965,0.693],[0,0]],"v":[[-31.448,23.889],[-66.675,35.451]],"c":false}]},{"i":{"x":0.667,"y":1},"o":{"x":0.167,"y":0.167},"t":20,"s":[{"i":[[0,0],[10.217,-6.711]],"o":[[-12.965,0.693],[0,0]],"v":[[-31.448,23.889],[-66.675,35.451]],"c":false}]},{"t":100,"s":[{"i":[[0,0],[10.217,-6.711]],"o":[[-12.965,0.693],[0,0]],"v":[[-31.448,23.889],[-66.675,35.451]],"c":false}]}],"ix":2},"nm":"Trazado 5","mn":"ADBE Vector Shape - Group","hd":false},{"ind":5,"ty":"sh","ix":6,"ks":{"a":1,"k":[{"i":{"x":0.833,"y":0.833},"o":{"x":0.333,"y":0},"t":5,"s":[{"i":[[0,0],[0,0],[0,0],[37.578,2.009]],"o":[[0,0],[0,0],[0,-38.079],[0,0]],"v":[[-39.626,146.804],[68.348,146.804],[68.348,95.081],[0.917,23.889]],"c":false}]},{"i":{"x":0.833,"y":0.833},"o":{"x":0.167,"y":0.167},"t":20,"s":[{"i":[[0,0],[-17.483,0.569],[0,0],[37.578,2.009]],"o":[[0,0],[8.617,-8.731],[0,-38.079],[0,0]],"v":[[-39.626,146.804],[59.431,146.867],[68.348,95.081],[0.917,23.889]],"c":false}]},{"i":{"x":0.667,"y":1},"o":{"x":0.167,"y":0.167},"t":70,"s":[{"i":[[0,0],[-29.138,0.948],[0,0],[37.578,2.009]],"o":[[0,0],[14.362,-14.552],[0,-38.079],[0,0]],"v":[[-39.626,146.804],[53.486,146.909],[68.348,95.081],[0.917,23.889]],"c":false}]},{"t":100,"s":[{"i":[[0,0],[0,0],[0,0],[37.578,2.009]],"o":[[0,0],[0,0],[0,-38.079],[0,0]],"v":[[-39.626,146.804],[68.348,146.804],[68.348,95.081],[0.917,23.889]],"c":false}]}],"ix":2},"nm":"Trazado 6","mn":"ADBE Vector Shape - Group","hd":false},{"ind":6,"ty":"sh","ix":7,"ks":{"a":1,"k":[{"i":{"x":0.833,"y":0.833},"o":{"x":0.333,"y":0},"t":5,"s":[{"i":[[0,0],[0,5.567],[-15.893,-1.086],[-0.605,-13.707],[3.079,-4.628]],"o":[[-2.869,-4.312],[0,-15.661],[13.689,0.936],[0.267,6.034],[0,0]],"v":[[-37.934,-103.518],[-42.478,-118.571],[-13.354,-145.718],[11.919,-119.801],[7.403,-103.518]],"c":false}]},{"i":{"x":0.833,"y":0.833},"o":{"x":0.167,"y":0.167},"t":20,"s":[{"i":[[0,0],[0.471,5.534],[-15.89,0.266],[-1.763,-13.573],[2.669,-4.861]],"o":[[-3.217,-4.043],[-1.326,-15.567],[13.686,-0.229],[0.776,5.975],[0,0]],"v":[[-47.701,-100.971],[-53.493,-115.549],[-26.843,-144.999],[0.473,-121.378],[-2.637,-104.811]],"c":false}]},{"i":{"x":0.667,"y":1},"o":{"x":0.167,"y":0.167},"t":70,"s":[{"i":[[0,0],[0.786,5.511],[-15.887,1.167],[-2.535,-13.484],[2.395,-5.016]],"o":[[-3.449,-3.864],[-2.211,-15.504],[13.684,-1.006],[1.116,5.936],[0,0]],"v":[[-54.213,-99.273],[-60.836,-113.534],[-35.836,-144.52],[-7.157,-122.43],[-9.33,-105.673]],"c":false}]},{"t":100,"s":[{"i":[[0,0],[0,5.567],[-15.893,-1.086],[-0.605,-13.707],[3.079,-4.628]],"o":[[-2.869,-4.312],[0,-15.661],[13.689,0.936],[0.267,6.034],[0,0]],"v":[[-37.934,-103.518],[-42.478,-118.571],[-13.354,-145.718],[11.919,-119.801],[7.403,-103.518]],"c":false}]}],"ix":2},"nm":"Trazado 7","mn":"ADBE Vector Shape - Group","hd":false},{"ty":"mm","mm":1,"nm":"Combinar trazados 1","mn":"ADBE Vector Filter - Merge","hd":false},{"ty":"st","c":{"a":0,"k":[0,0,0,1],"ix":3,"x":"var $bm_rt;\n$bm_rt = thisComp.layer('Main Stroke width - Color Ctrl').effect('Base Color')('ADBE Color Control-0001');"},"o":{"a":0,"k":100,"ix":4},"w":{"a":0,"k":15.4,"ix":5,"x":"var $bm_rt;\n$bm_rt = thisComp.layer('Main Stroke width - Color Ctrl').effect('Stroke width')('ADBE Slider Control-0001');"},"lc":2,"lj":2,"bm":0,"nm":"Trazo 1","mn":"ADBE Vector Graphic - Stroke","hd":false},{"ty":"tr","p":{"a":0,"k":[106.848,185.304],"ix":2},"a":{"a":0,"k":[0,0],"ix":1},"s":{"a":0,"k":[100,100],"ix":3},"r":{"a":0,"k":0,"ix":6},"o":{"a":0,"k":100,"ix":7},"sk":{"a":0,"k":0,"ix":4},"sa":{"a":0,"k":0,"ix":5},"nm":"Transformar"}],"nm":"Grupo 1","np":9,"cix":2,"bm":0,"ix":1,"mn":"ADBE Vector Group","hd":false}],"ip":0,"op":115,"st":0,"bm":0},{"ddd":0,"ind":7,"ty":4,"nm":"Heart","sr":1,"ks":{"o":{"a":0,"k":100,"ix":11},"r":{"a":1,"k":[{"i":{"x":[0.833],"y":[1]},"o":{"x":[0.333],"y":[0]},"t":5,"s":[0]},{"i":{"x":[0.667],"y":[1]},"o":{"x":[0.167],"y":[0]},"t":58,"s":[10]},{"t":110,"s":[0]}],"ix":10},"p":{"a":1,"k":[{"i":{"x":0.833,"y":0.832},"o":{"x":0.333,"y":0},"t":5,"s":[256,120.538,0],"to":[0,0,0],"ti":[0,0,0]},{"i":{"x":0.667,"y":1},"o":{"x":0.167,"y":0.165},"t":58,"s":[256,77.538,0],"to":[0,0,0],"ti":[0,0,0]},{"t":110,"s":[256,120.538,0]}],"ix":2,"l":2},"a":{"a":0,"k":[256,51.538,0],"ix":1,"l":2},"s":{"a":0,"k":[100,100,100],"ix":6,"l":2}},"ao":0,"shapes":[{"ty":"gr","it":[{"ind":0,"ty":"sh","ix":1,"ks":{"a":1,"k":[{"i":{"x":0.833,"y":0.833},"o":{"x":0.333,"y":0},"t":5,"s":[{"i":[[0,0],[0,0],[0,10.768],[-13.225,-0.573],[-4.043,-4.897],[-6.774,0.295],[0,-13.237],[8.493,-6.619]],"o":[[0,0],[-8.493,-6.619],[0,-13.237],[6.774,0.294],[4.043,-4.897],[13.225,-0.575],[0,10.768],[0,0]],"v":[[0,36.537],[-27.541,15.068],[-41,-12.485],[-16.835,-35.962],[0,-27.566],[16.835,-35.962],[41,-12.485],[27.541,15.068]],"c":true}]},{"i":{"x":0.833,"y":0.833},"o":{"x":0.167,"y":0.167},"t":31,"s":[{"i":[[0,0],[0,0],[0,8.93],[-10.967,-0.475],[-3.353,-4.061],[-5.617,0.244],[0,-10.977],[7.043,-5.489]],"o":[[0,0],[-7.043,-5.489],[0,-10.977],[5.617,0.243],[3.353,-4.061],[10.967,-0.477],[0,8.93],[0,0]],"v":[[0,30.299],[-22.839,12.496],[-34,-10.354],[-13.961,-29.822],[0,-22.86],[13.961,-29.822],[34,-10.354],[22.839,12.496]],"c":true}]},{"i":{"x":0.833,"y":0.833},"o":{"x":0.167,"y":0.167},"t":58,"s":[{"i":[[0,0],[0,0],[0,11.996],[-14.733,-0.639],[-4.505,-5.455],[-7.546,0.328],[0,-14.747],[9.461,-7.373]],"o":[[0,0],[-9.461,-7.373],[0,-14.747],[7.546,0.327],[4.504,-5.455],[14.733,-0.641],[0,11.996],[0,0]],"v":[[0,40.703],[-30.682,16.786],[-45.675,-13.909],[-18.754,-40.062],[0,-30.709],[18.754,-40.062],[45.675,-13.909],[30.682,16.786]],"c":true}]},{"i":{"x":0.667,"y":1},"o":{"x":0.167,"y":0.167},"t":85,"s":[{"i":[[0,0],[0,0],[0,8.93],[-10.967,-0.475],[-3.353,-4.061],[-5.617,0.244],[0,-10.977],[7.043,-5.489]],"o":[[0,0],[-7.043,-5.489],[0,-10.977],[5.617,0.243],[3.353,-4.061],[10.967,-0.477],[0,8.93],[0,0]],"v":[[0,30.299],[-22.839,12.496],[-34,-10.354],[-13.961,-29.822],[0,-22.86],[13.961,-29.822],[34,-10.354],[22.839,12.496]],"c":true}]},{"t":110,"s":[{"i":[[0,0],[0,0],[0,10.768],[-13.225,-0.573],[-4.043,-4.897],[-6.774,0.295],[0,-13.237],[8.493,-6.619]],"o":[[0,0],[-8.493,-6.619],[0,-13.237],[6.774,0.294],[4.043,-4.897],[13.225,-0.575],[0,10.768],[0,0]],"v":[[0,36.537],[-27.541,15.068],[-41,-12.485],[-16.835,-35.962],[0,-27.566],[16.835,-35.962],[41,-12.485],[27.541,15.068]],"c":true}]}],"ix":2},"nm":"Trazado 1","mn":"ADBE Vector Shape - Group","hd":false},{"ty":"st","c":{"a":0,"k":[0.20000001496,0.800000059838,0.800000059838,1],"ix":3,"x":"var $bm_rt;\n$bm_rt = thisComp.layer('Main Stroke width - Color Ctrl').effect('Highlight')('ADBE Color Control-0001');"},"o":{"a":0,"k":100,"ix":4},"w":{"a":0,"k":15.4,"ix":5,"x":"var $bm_rt;\n$bm_rt = thisComp.layer('Main Stroke width - Color Ctrl').effect('Stroke width')('ADBE Slider Control-0001');"},"lc":2,"lj":2,"bm":0,"nm":"Trazo 1","mn":"ADBE Vector Graphic - Stroke","hd":false},{"ty":"tr","p":{"a":0,"k":[256,51.297],"ix":2},"a":{"a":0,"k":[0,0],"ix":1},"s":{"a":0,"k":[100,100],"ix":3},"r":{"a":0,"k":0,"ix":6},"o":{"a":0,"k":100,"ix":7},"sk":{"a":0,"k":0,"ix":4},"sa":{"a":0,"k":0,"ix":5},"nm":"Transformar"}],"nm":"Grupo 1","np":2,"cix":2,"bm":0,"ix":1,"mn":"ADBE Vector Group","hd":false}],"ip":0,"op":115,"st":0,"bm":0},{"ddd":0,"ind":8,"ty":3,"nm":"Zero | troke width - Color Ctrl","sr":1,"ks":{"o":{"a":0,"k":0,"ix":11},"r":{"a":0,"k":0,"ix":10},"p":{"a":0,"k":[250,250,0],"ix":2,"l":2},"a":{"a":0,"k":[0,0,0],"ix":1,"l":2},"s":{"a":0,"k":[100,100,100],"ix":6,"l":2}},"ao":0,"ip":0,"op":115,"st":0,"bm":0}],"markers":[]}